matrix_manipulation_aharas/__init__.py
matrix_manipulation_aharas/classes.py
matrix_manipulation_aharas/decorators.py
matrix_manipulation_aharas/helpers.py
matrix_manipulation_aharas/tests/test.py
matrix_manipulation_aharas-0.4.2.dist-info/METADATA
matrix_manipulation_aharas-0.4.2.dist-info/WHEEL
matrix_manipulation_aharas-0.4.2.dist-info/RECORD
