Metadata-Version: 2.1
Name: matrix_manipulation_aharas
Version: 0.4.2
Summary: 
Author: hvsio
Author-email: alicjaharaszczuk@gmail.com
Requires-Python: >=3.9,<3.13
Classifier: Programming Language :: Python :: 3
Classifier: Programming Language :: Python :: 3.9
Classifier: Programming Language :: Python :: 3.10
Classifier: Programming Language :: Python :: 3.11
Requires-Dist: numpy (>=1.26.1,<2.0.0)
